.coveragerc
.travis.yml
LICENSE
MANIFEST.in
README.rst
setup.cfg
setup.py
Mopidy_TtsGpio.egg-info/PKG-INFO
Mopidy_TtsGpio.egg-info/SOURCES.txt
Mopidy_TtsGpio.egg-info/dependency_links.txt
Mopidy_TtsGpio.egg-info/entry_points.txt
Mopidy_TtsGpio.egg-info/not-zip-safe
Mopidy_TtsGpio.egg-info/requires.txt
Mopidy_TtsGpio.egg-info/top_level.txt
mopidy_ttsgpio/__init__.py
mopidy_ttsgpio/ext.conf
mopidy_ttsgpio/frontend.py
mopidy_ttsgpio/gpio_input_manager.py
mopidy_ttsgpio/gpio_simulator.py
mopidy_ttsgpio/main_menu.py
mopidy_ttsgpio/on_off_configuration.py
mopidy_ttsgpio/playlist_menu.py
mopidy_ttsgpio/tts.py
tests/__init__.py
tests/test_extension.py