Metadata-Version: 1.1
Name: Mopidy-TtsGpio
Version: 1.0.2
Summary: Controll mopidy without screen using GPIO and TTS
Home-page: https://github.com/9and3r/mopidy-ttsgpio
Author: 9and3r
Author-email: 9and3r@gmail.com
License: Apache License, Version 2.0
Platform: UNKNOWN
Classifier: Environment :: No Input/Output (Daemon)
Classifier: Intended Audience :: End Users/Desktop
Classifier: License :: OSI Approved :: Apache Software License
Classifier: Operating System :: OS Independent
Classifier: Programming Language :: Python :: 2
Classifier: Topic :: Multimedia :: Sound/Audio :: Players
